slower/__init__.py
slower-0.0.1.dist-info/METADATA
slower-0.0.1.dist-info/WHEEL
slower-0.0.1.dist-info/top_level.txt
slower-0.0.1.dist-info/RECORD
