Metadata-Version: 2.1
Name: slower
Version: 0.0.1
Summary: Make things slower
Author-email: Hudson Cooper <hncooper96@gmail.com>
Project-URL: source, https://github.com/hudson-ai/slower
Project-URL: download, https://pypi.org/project/slower/#files
Provides-Extra: dev
Requires-Dist: pytest ; extra == 'dev'
Requires-Dist: pytest-asyncio ; extra == 'dev'
